LICENSE
MANIFEST.in
README
README.md
requirements.txt
setup.py
majorapi/__init__.py
majorapi/error.py
majorapi/quickbooks.py
majorapi_python_sdk.egg-info/PKG-INFO
majorapi_python_sdk.egg-info/SOURCES.txt
majorapi_python_sdk.egg-info/dependency_links.txt
majorapi_python_sdk.egg-info/requires.txt
majorapi_python_sdk.egg-info/top_level.txt