Metadata-Version: 1.0
Name: majorapi-python-sdk
Version: 0.1.0
Summary: The MajorApi Python SDK
Home-page: http://github.com/brightmarch/majorapi-python-sdk
Author: Rod Afshar
Author-email: rafshar@gmail.com
License: MIT
Keywords: majorapi
Platform: UNKNOWN
Classifier: Programming Language :: Python
Classifier: Development Status :: 4 - Beta
Classifier: License :: OSI Approved :: MIT License
Classifier: Operating System :: OS Independent
Classifier: Intended Audience :: Developers
